[
  {
    "inputs": [
      {
        "internalType": "bytes32",
        "name": "hash",
        "type": "bytes32"
      },
      {
        "internalType": "uint8",
        "name": "v",
        "type": "uint8"
      },
      {
        "internalType": "bytes32",
        "name": "r",
        "type": "bytes32"
      },
      {
        "internalType": "bytes32",
        "name": "s",
        "type": "bytes32"
      }
    ],
    "name": "_ecrecover",
    "outputs": [
      {
        "internalType": "address",
        "name": "",
        "type": "address"
      }
    ],
    "stateMutability": "pure",
    "type": "function"
  },
  {
    "inputs": [
      {
        "internalType": "bytes",
        "name": "_msg",
        "type": "bytes"
      }
    ],
    "name": "getMsgHash",
    "outputs": [
      {
        "internalType": "bytes32",
        "name": "",
        "type": "bytes32"
      }
    ],
    "stateMutability": "pure",
    "type": "function"
  }
]
